{"actions": [{"start": 4, "end": 201, "id": 0, "type": "passe", "passeur": 4, "receveur": 5, "team_passeur": 0, "team_receveur": 0, "succeed": true}, {"start": 555, "end": 725, "id": 1, "type": "passe", "passeur": 5, "receveur": 6, "team_passeur": 1, "team_receveur": 1, "succeed": true}, {"start": 776, "end": 895, "id": 2, "type": "passe", "passeur": 1, "receveur": 5, "team_passeur": 1, "team_receveur": 1, "succeed": true}, {"start": 990, "end": 1023, "id": 3, "type": "passe", "passeur": 5, "receveur": 21, "team_passeur": 1, "team_receveur": 1, "succeed": true}, {"start": 1087, "end": 1124, "id": 4, "type": "passe", "passeur": 21, "receveur": 7, "team_passeur": 1, "team_receveur": 1, "succeed": true}, {"start": 1186, "end": 1242, "id": 5, "type": "passe", "passeur": 7, "receveur": 2, "team_passeur": 1, "team_receveur": 1, "succeed": true}, {"start": 1245, "end": 1305, "id": 6, "type": "passe", "passeur": 2, "receveur": 4, "team_passeur": 0, "team_receveur": 0, "succeed": true}, {"start": 1327, "end": 1614, "id": 7, "type": "passe", "passeur": 3, "receveur": 15, "team_passeur": 1, "team_receveur": 1, "succeed": true}, {"start": 1845, "end": 2112, "id": 8, "type": "passe", "passeur": 15, "receveur": 14, "team_passeur": 1, "team_receveur": 1, "succeed": true}, {"start": 2154, "end": 2270, "id": 9, "type": "passe", "passeur": 6, "receveur": 11, "team_passeur": 0, "team_receveur": 0, "succeed": true}]}